findaureus/Module_Class.py
findaureus/__init__.py
findaureus/_reader.py
findaureus/_sample_data.py
findaureus/_widget.py
findaureus/_writer.py
findaureus/napari.yaml
findaureus/_tests/__init__.py
findaureus/_tests/test_reader.py
findaureus/_tests/test_sample_data.py
findaureus/_tests/test_widget.py
findaureus/_tests/test_writer.py
findaureus/resources/Findaureus icon.svg
findaureus/resources/GitHub-Mark-Light-32px.png
findaureus/resources/application_icon.png
napari_findaureus-0.0.4.dist-info/LICENSE
napari_findaureus-0.0.4.dist-info/METADATA
napari_findaureus-0.0.4.dist-info/WHEEL
napari_findaureus-0.0.4.dist-info/entry_points.txt
napari_findaureus-0.0.4.dist-info/top_level.txt
napari_findaureus-0.0.4.dist-info/RECORD
