Metadata-Version: 2.1
Name: napari-findaureus
Version: 0.0.4
Summary: Locate bacteria in CLSM obtained infected bone tissue images
Author: Shibarjun Mandal
Author-email: shibarjunmandal@gmail.com
License: MIT
Classifier: Development Status :: 2 - Pre-Alpha
Classifier: Framework :: napari
Classifier: Intended Audience :: Developers
Classifier: License :: OSI Approved :: MIT License
Classifier: Operating System :: OS Independent
Classifier: Programming Language :: Python
Classifier: Programming Language :: Python :: 3
Classifier: Programming Language :: Python :: 3 :: Only
Classifier: Programming Language :: Python :: 3.8
Classifier: Programming Language :: Python :: 3.9
Classifier: Programming Language :: Python :: 3.10
Classifier: Topic :: Scientific/Engineering :: Image Processing
Requires-Python: >=3.8
License-File: LICENSE
Requires-Dist: magicgui
Requires-Dist: qtpy
Requires-Dist: napari[all]
Requires-Dist: aicsimageio ==4.11.0
Requires-Dist: nd2 ==0.5.3
Requires-Dist: aicspylibczi ==3.1.2
Requires-Dist: fsspec ==2023.5.0
Requires-Dist: readlif ==0.6.5
Requires-Dist: czifile ==2019.7.2
Requires-Dist: tifffile ==2023.7.10
Requires-Dist: webcolors ==1.13
Requires-Dist: opencv-python ==4.7.0.72
Requires-Dist: numpy ==1.24.3
Requires-Dist: scikit-image ==0.20.0
Requires-Dist: xmltodict
Provides-Extra: testing
Requires-Dist: tox ; extra == 'testing'
Requires-Dist: pytest ; extra == 'testing'
Requires-Dist: pytest-cov ; extra == 'testing'
Requires-Dist: pytest-qt ; extra == 'testing'
Requires-Dist: napari ; extra == 'testing'
Requires-Dist: pyqt5 ; extra == 'testing'
